wagtail_meilisearch/__init__.py
wagtail_meilisearch/backend.py
wagtail_meilisearch/defaults.py
wagtail_meilisearch/index.py
wagtail_meilisearch/management/__init__.py
wagtail_meilisearch/management/commands/__init__.py
wagtail_meilisearch/management/commands/meilisearch_indexes.py
wagtail_meilisearch/management/commands/meilisearch_status.py
wagtail_meilisearch/py.typed
wagtail_meilisearch/query.py
wagtail_meilisearch/rebuilder.py
wagtail_meilisearch/results.py
wagtail_meilisearch/settings.py
wagtail_meilisearch/utils.py
wagtail_meilisearch-1.1.0.dist-info/WHEEL
wagtail_meilisearch-1.1.0.dist-info/METADATA
wagtail_meilisearch-1.1.0.dist-info/RECORD
