Metadata-Version: 2.3
Name: wagtail-meilisearch
Version: 1.1.0
Summary: A MeiliSearch backend for Wagtail
Author: Hactar
Author-email: Hactar <systems@hactar.is>
Requires-Dist: arrow>=1.2.3
Requires-Dist: wagtail>=6.0
Requires-Dist: meilisearch>=0.36.0
Requires-Python: >=3.10
